nonogram_cracker/__init__.py
nonogram_cracker/schemas.py
nonogram_cracker/solution_response.py
nonogram_cracker/solve.py
nonogram_cracker/solve_seq.py
nonogram_cracker/helpers/__init__.py
nonogram_cracker/helpers/converter.py
nonogram_cracker/helpers/identifiers.py
nonogram_cracker/helpers/is_solved.py
nonogram_cracker/helpers/segmentation.py
nonogram_cracker-1.0.1.dist-info/LICENSE
nonogram_cracker-1.0.1.dist-info/METADATA
nonogram_cracker-1.0.1.dist-info/WHEEL
nonogram_cracker-1.0.1.dist-info/top_level.txt
nonogram_cracker-1.0.1.dist-info/RECORD
