Metadata-Version: 2.1
Name: nonogram-cracker
Version: 1.0.1
Summary: A standalone function that returns the solution of a nonogram puzzle.
Home-page: https://gitlab.com/caseyvangroll/nonogram_cracker
Author: Casey Van Groll
Author-email: caseyvangroll@gmail.com
License: UNKNOWN
Project-URL: Bug Tracker, https://gitlab.com/caseyvangroll/nonogram_cracker/issues
Platform: UNKNOWN
Classifier: Programming Language :: Python :: 3
Classifier: License :: OSI Approved :: MIT License
Classifier: Operating System :: OS Independent
Requires-Python: >=3.6
License-File: LICENSE
